odoo/addons/base_rule_visibility_restriction/README.rst
odoo/addons/base_rule_visibility_restriction/__init__.py
odoo/addons/base_rule_visibility_restriction/__manifest__.py
odoo/addons/base_rule_visibility_restriction/i18n/base_rule_visibility_restriction.pot
odoo/addons/base_rule_visibility_restriction/i18n/it.po
odoo/addons/base_rule_visibility_restriction/models/__init__.py
odoo/addons/base_rule_visibility_restriction/models/ir_rule.py
odoo/addons/base_rule_visibility_restriction/readme/CONTRIBUTORS.rst
odoo/addons/base_rule_visibility_restriction/readme/DESCRIPTION.rst
odoo/addons/base_rule_visibility_restriction/readme/USAGE.rst
odoo/addons/base_rule_visibility_restriction/static/description/icon.png
odoo/addons/base_rule_visibility_restriction/static/description/index.html
odoo/addons/base_rule_visibility_restriction/views/ir_rule_views.xml
odoo14_addon_base_rule_visibility_restriction-14.0.1.0.1.dev6.dist-info/METADATA
odoo14_addon_base_rule_visibility_restriction-14.0.1.0.1.dev6.dist-info/WHEEL
odoo14_addon_base_rule_visibility_restriction-14.0.1.0.1.dev6.dist-info/top_level.txt
odoo14_addon_base_rule_visibility_restriction-14.0.1.0.1.dev6.dist-info/RECORD
